togpush/__init__.py
togpush/data_filters.py
togpush/fsm.py
togpush/protobuf/__init__.py
togpush/protobuf/labels_pb2.py
togpush/tog.py
togpush/utils.py
togpush-1.1.15.dist-info/entry_points.txt
togpush-1.1.15.dist-info/WHEEL
togpush-1.1.15.dist-info/METADATA
togpush-1.1.15.dist-info/RECORD
